pdb_multi.py
pdb_multi-1.1.dist-info/METADATA
pdb_multi-1.1.dist-info/WHEEL
pdb_multi-1.1.dist-info/top_level.txt
pdb_multi-1.1.dist-info/RECORD
