Metadata-Version: 2.1
Name: pdb_multi
Version: 1.1
Summary: Pdb designed for multiprocessing
Home-page: https://github.com/claserken/pdb-multi
